swjas
