Metadata-Version: 2.1
Name: swjas
Version: 0.1.0
Summary: Simple WSGI JSON API Server
Home-page: https://github.com/francescozoccheddu/swjas
Author: Francesco Zoccheddu
License: MIT
Platform: UNKNOWN
Classifier: License :: OSI Approved :: MIT License
Classifier: Programming Language :: Python :: 3
Classifier: Programming Language :: Python :: 3.7
